mailipy/__init__.py
mailipy/gen.py
mailipy/gen_test.py
mailipy/send.py
mailipy/send_test.py
mailipy-0.1.0.dist-info/LICENSE
mailipy-0.1.0.dist-info/METADATA
mailipy-0.1.0.dist-info/WHEEL
mailipy-0.1.0.dist-info/entry_points.txt
mailipy-0.1.0.dist-info/RECORD
