Metadata-Version: 2.1
Name: mailipy
Version: 0.1.0
Summary: A handy CLI tool for bulk-sending emails
License: MIT
Author: William Di Luigi
Author-email: williamdiluigi@gmail.com
Requires-Python: >=3.8
Classifier: License :: OSI Approved :: MIT License
Classifier: Programming Language :: Python :: 3
Classifier: Programming Language :: Python :: 3.8
Classifier: Programming Language :: Python :: 3.9
Classifier: Programming Language :: Python :: 3.10
Classifier: Programming Language :: Python :: 3.11
Classifier: Programming Language :: Python :: 3.12
Classifier: Programming Language :: Python :: 3.13
Requires-Dist: jinja2 (>=3.1.5,<4.0.0)
Requires-Dist: markdown (>=3.7,<4.0)
Requires-Dist: pyyaml (>=6.0.2,<7.0.0)
